pytest_markdown_docs/__init__.py
pytest_markdown_docs/_runners.py
pytest_markdown_docs/definitions.py
pytest_markdown_docs/hooks.py
pytest_markdown_docs/plugin.py
pytest_markdown_docs/py.typed
pytest_markdown_docs-0.9.0.dist-info/METADATA
pytest_markdown_docs-0.9.0.dist-info/WHEEL
pytest_markdown_docs-0.9.0.dist-info/entry_points.txt
pytest_markdown_docs-0.9.0.dist-info/licenses/LICENSE
pytest_markdown_docs-0.9.0.dist-info/RECORD
