Metadata-Version: 2.4
Name: pytest-markdown-docs
Version: 0.9.0
Summary: Run markdown code fences through pytest
Author: Modal Labs
Author-email: Elias Freider <elias@modal.com>
License-Expression: MIT
License-File: LICENSE
Requires-Python: >=3.9
Requires-Dist: markdown-it-py<4.0,>=2.2.0
Requires-Dist: pytest>=7.0.0
